navicat_marc/__init__.py
navicat_marc/__main__.py
navicat_marc/clustering.py
navicat_marc/da.py
navicat_marc/distatis.py
navicat_marc/erel.py
navicat_marc/exceptions.py
navicat_marc/helpers.py
navicat_marc/marc.py
navicat_marc/molecule.py
navicat_marc/rmsd.py
navicat_marc/test_modules.py
navicat_marc-0.2.7.dist-info/LICENSE
navicat_marc-0.2.7.dist-info/METADATA
navicat_marc-0.2.7.dist-info/WHEEL
navicat_marc-0.2.7.dist-info/entry_points.txt
navicat_marc-0.2.7.dist-info/top_level.txt
navicat_marc-0.2.7.dist-info/RECORD
